LICENSE
cookietools/__init__.py
cookietools/py.typed
python_cookietools-0.1.3.dist-info/LICENSE
python_cookietools-0.1.3.dist-info/METADATA
python_cookietools-0.1.3.dist-info/WHEEL
python_cookietools-0.1.3.dist-info/RECORD
